seqhelp/__init__.py
seqhelp/codon.py
seqhelp/codon_pair.py
seqhelp/common.py
seqhelp/dinucleotides.py
seqhelp/gc_content.py
seqhelp/relations.py
seqhelp/sequences.py
seqhelp/taxonomy.py
seqhelp/virus_hosts.py
seqhelp/virushostdb.tsv.bak
seqhelp-0.2.2.dist-info/METADATA
seqhelp-0.2.2.dist-info/WHEEL
seqhelp-0.2.2.dist-info/RECORD
